script2stlite/__init__.py
script2stlite/functions.py
script2stlite/script2stlite.py
script2stlite/templates/html_template.txt
script2stlite/templates/settings.yaml
script2stlite-0.2.1.dist-info/LICENSE
script2stlite-0.2.1.dist-info/METADATA
script2stlite-0.2.1.dist-info/WHEEL
script2stlite-0.2.1.dist-info/RECORD
