Metadata-Version: 2.1
Name: script2stlite
Version: 0.2.1
Summary: Package to convert a streamlit script and files to an stlite app (https://github.com/whitphx/stlite)
Home-page: https://github.com/LukeAFullard/script2stlite
License: MIT
Author: LukeAFullard
Requires-Python: >=3.8,<4.0
Classifier: License :: OSI Approved :: MIT License
Classifier: Programming Language :: Python :: 3
Classifier: Programming Language :: Python :: 3.8
Classifier: Programming Language :: Python :: 3.9
Classifier: Programming Language :: Python :: 3.10
Classifier: Programming Language :: Python :: 3.11
Classifier: Programming Language :: Python :: 3.12
Requires-Dist: PyYAML (>=6.0.0,<7.0.0)
Requires-Dist: requests (>=2.27.0,<3.0.0)
Requires-Dist: tomli (>=2.0.0,<3.0.0)
Project-URL: Repository, https://github.com/LukeAFullard/script2stlite
